Metadata-Version: 1.0
Name: distributions-by-harry
Version: 0.1
Summary: Gaussian and Binomial distributions
Home-page: UNKNOWN
Author: Hari Prasanth
Author-email: harrymechatron@gmail.com
License: UNKNOWN
Platform: UNKNOWN
